{
  "assessments": [],
  "controls": [
    {
      "id": "d718f39b-2403-4663-8ec7-bb5b02095f95",
      "controlCode": "UD-00010",
      "controlType": "REGEX",
      "domainId": 1,
      "name": "Juniper Version Check",
      "description": "This control uses regex to extract JunOS versions.",
      "severity": 1,
      "system": false,
      "properties": [
        {
          "controlId": "d718f39b-2403-4663-8ec7-bb5b02095f95",
          "controlType": "REGEX",
          "name": "FailWhenResultsExist",
          "type": "BOOLEAN",
          "displayName": "Fail When Results Exist",
          "required": true,
          "booleanValue": true
        },
        {
          "controlId": "d718f39b-2403-4663-8ec7-bb5b02095f95",
          "controlType": "REGEX",
          "name": "FilenamesToSearch",
          "type": "STRING",
          "displayName": "Filenames To Search",
          "required": false,
          "string": "config_xml"
        },
        {
          "controlId": "d718f39b-2403-4663-8ec7-bb5b02095f95",
          "controlType": "REGEX",
          "name": "InfoOnly",
          "type": "BOOLEAN",
          "displayName": "Information Only",
          "required": true,
          "booleanValue": true
        },
        {
          "controlId": "d718f39b-2403-4663-8ec7-bb5b02095f95",
          "controlType": "REGEX",
          "name": "MaxLineLength",
          "type": "INTEGER",
          "displayName": "Max Line Length",
          "required": true,
          "integerValue": 160
        },
        {
          "controlId": "d718f39b-2403-4663-8ec7-bb5b02095f95",
          "controlType": "REGEX",
          "name": "Pattern",
          "type": "STRING",
          "displayName": "Pattern",
          "required": true,
          "string": "<rpc-reply xmlns:junos=\\\"http://xml.juniper.net/junos/([^/]+)/junos\\\">"
        },
        {
          "controlId": "d718f39b-2403-4663-8ec7-bb5b02095f95",
          "controlType": "REGEX",
          "name": "SearchAllFiles",
          "type": "BOOLEAN",
          "displayName": "Search All Files",
          "required": true,
          "booleanValue": false
        }
      ],
      "filters": [
        {
          "id": "04c74234-1452-4cb7-ae4a-607a94f6d5af",
          "type": "DEVICE_TYPE",
          "deviceType": "DEVICE_MGR"
        },
        {
          "id": "bc33ef7f-03c6-413c-9f12-bbbad339f2e0",
          "type": "DEVICE_TYPE",
          "deviceType": "FIREWALL"
        },
        {
          "id": "9935d0b3-6d63-4d2d-8fb4-40bd1504f038",
          "type": "VENDOR",
          "vendor": "Juniper Networks"
        },
        {
          "id": "93107cf3-4548-47e2-bdf1-e4b372fd82c3",
          "type": "DEVICE_TYPE",
          "deviceType": "ROUTER_SWITCH"
        }
      ],
      "createdBy": "firemon",
      "createdDate": "2024-07-18T19:24:48.910Z",
      "lastModifiedBy": "firemon",
      "lastModifiedDate": "2024-07-18T19:24:48.910Z",
      "observesSystemRules": false
    }
  ],
  "zones": [],
  "services": []
}
